[
    {
        "fullName": "Ryan Manchanda",
        "rollNumber": "CS25B1034",
        "startDate": "2026-01-05",
        "endDate": "2026-01-10",
        "totalDays": 6,
        "phone": "9234567890",
        "reason": "Family function",
        "status": "Approved",
        "refundStatus": "Refunded",
        "name": "Ryan Manchanda",
        "fatherName": "Rishi Manchanda",
        "motherName": "Mrs. Manchanda",
        "fatherPhone": "9501453725",
        "motherPhone": "9876543009",
        "parentPhone": "9501453725",
        "semester": 1,
        "year": 1,
        "hostelName": "Boys  Hostel A",
        "warden": "Mr. Ramesh Chand",
        "fa": "Dr. Bharat Soni",
        "messName": "Mess B",
        "bankName": "SBI",
        "bankAccountNumber": "10020001234567",
        "bankIfsc": "SBIN0001234",
        "branch": "Computer Science",
        "roomNumber": "A-101",
        "email": "cs25b1034@iiitr.ac.in"
    },
    {
        "fullName": "Ryan Manchanda",
        "rollNumber": "CS25B1034",
        "startDate": "2026-02-01",
        "endDate": "2026-02-03",
        "totalDays": 3,
        "phone": "9234567890",
        "reason": "Medical leave",
        "status": "Pending Warden Approval",
        "name": "Ryan Manchanda",
        "fatherName": "Rishi Manchanda",
        "motherName": "Mrs. Manchanda",
        "fatherPhone": "9501453725",
        "motherPhone": "9876543009",
        "parentPhone": "9501453725",
        "semester": 1,
        "year": 1,
        "hostelName": "Boys  Hostel A",
        "warden": "Mr. Ramesh Chand",
        "fa": "Dr. Bharat Soni",
        "messName": "Mess B",
        "bankName": "SBI",
        "bankAccountNumber": "10020001234567",
        "bankIfsc": "SBIN0001234",
        "branch": "Computer Science",
        "roomNumber": "A-101",
        "email": "cs25b1034@iiitr.ac.in"
    },
    {
        "fullName": "Ryan Manchanda",
        "rollNumber": "CS25B1034",
        "startDate": "2026-02-10",
        "endDate": "2026-02-15",
        "totalDays": 6,
        "phone": "9234567890",
        "reason": "Personal work",
        "status": "Pending Warden Approval",
        "name": "Ryan Manchanda",
        "fatherName": "Rishi Manchanda",
        "motherName": "Mrs. Manchanda",
        "fatherPhone": "9501453725",
        "motherPhone": "9876543009",
        "parentPhone": "9501453725",
        "semester": 1,
        "year": 1,
        "hostelName": "Boys  Hostel A",
        "warden": "Mr. Ramesh Chand",
        "fa": "Dr. Bharat Soni",
        "messName": "Mess B",
        "bankName": "SBI",
        "bankAccountNumber": "10020001234567",
        "bankIfsc": "SBIN0001234",
        "branch": "Computer Science",
        "roomNumber": "A-101",
        "email": "cs25b1034@iiitr.ac.in"
    },
    {
        "fullName": "Ryan Manchanda",
        "rollNumber": "CS25B1034",
        "startDate": "2026-02-14",
        "endDate": "2026-02-20",
        "totalDays": 7,
        "phone": "9234567890",
        "reason": "Home visit",
        "status": "Pending FA Approval",
        "name": "Ryan Manchanda",
        "fatherName": "Rishi Manchanda",
        "motherName": "Mrs. Manchanda",
        "fatherPhone": "9501453725",
        "motherPhone": "9876543009",
        "parentPhone": "9501453725",
        "semester": 1,
        "year": 1,
        "hostelName": "Boys  Hostel A",
        "warden": "Mr. Ramesh Chand",
        "fa": "Dr. Bharat Soni",
        "messName": "Mess B",
        "bankName": "SBI",
        "bankAccountNumber": "10020001234567",
        "bankIfsc": "SBIN0001234",
        "branch": "Computer Science",
        "roomNumber": "A-101",
        "email": "cs25b1034@iiitr.ac.in"
    },
    {
        "fullName": "Ryan Manchanda",
        "rollNumber": "CS25B1034",
        "startDate": "2026-02-18",
        "endDate": "2026-02-19",
        "totalDays": 2,
        "phone": "9234567890",
        "reason": "Doctor appointment",
        "status": "Rejected",
        "name": "Ryan Manchanda",
        "fatherName": "Rishi Manchanda",
        "motherName": "Mrs. Manchanda",
        "fatherPhone": "9501453725",
        "motherPhone": "9876543009",
        "parentPhone": "9501453725",
        "semester": 1,
        "year": 1,
        "hostelName": "Boys  Hostel A",
        "warden": "Mr. Ramesh Chand",
        "fa": "Dr. Bharat Soni",
        "messName": "Mess B",
        "bankName": "SBI",
        "bankAccountNumber": "10020001234567",
        "bankIfsc": "SBIN0001234",
        "branch": "Computer Science",
        "roomNumber": "A-101",
        "email": "cs25b1034@iiitr.ac.in"
    },
    {
        "fullName": "Ryan Manchanda",
        "rollNumber": "CS25B1034",
        "startDate": "2026-01-20",
        "endDate": "2026-01-25",
        "totalDays": 6,
        "phone": "9234567890",
        "reason": "Family emergency",
        "status": "Approved",
        "refundStatus": "Processing",
        "name": "Ryan Manchanda",
        "fatherName": "Rishi Manchanda",
        "motherName": "Mrs. Manchanda",
        "fatherPhone": "9501453725",
        "motherPhone": "9876543009",
        "parentPhone": "9501453725",
        "semester": 1,
        "year": 1,
        "hostelName": "Boys  Hostel A",
        "warden": "Mr. Ramesh Chand",
        "fa": "Dr. Bharat Soni",
        "messName": "Mess B",
        "bankName": "SBI",
        "bankAccountNumber": "10020001234567",
        "bankIfsc": "SBIN0001234",
        "branch": "Computer Science",
        "roomNumber": "A-101",
        "email": "cs25b1034@iiitr.ac.in"
    },
    {
        "fullName": "Ryan Manchanda",
        "rollNumber": "CS25B1034",
        "fatherName": "Rishi Manchanda",
        "motherName": "Mrs. Manchanda",
        "phone": "9234567890",
        "fatherPhone": "9501453725",
        "motherPhone": "9876543009",
        "parentPhone": "9501453725",
        "parentRelation": "father",
        "year": 1,
        "semester": 1,
        "hostelName": "Boys  Hostel A",
        "warden": "Mr. Ramesh Chand",
        "fa": "Dr. Bharat Soni",
        "messName": "Mess B",
        "bankName": "SBI",
        "bankAccountNumber": "10020001234567",
        "bankIfsc": "SBIN0001234",
        "startDate": "2026-02-24",
        "endDate": "2026-02-28",
        "totalDays": 5,
        "reason": "iobiscj",
        "status": "Pending Warden Approval",
        "refundStatus": "Awaiting Approval",
        "name": "Ryan Manchanda",
        "branch": "Computer Science",
        "roomNumber": "A-101",
        "email": "cs25b1034@iiitr.ac.in"
    },
    {
        "fullName": "Ryan Manchanda",
        "rollNumber": "CS25B1034",
        "fatherName": "Rishi Manchanda",
        "motherName": "Mrs. Manchanda",
        "phone": "9234567890",
        "fatherPhone": "9501453725",
        "motherPhone": "9876543009",
        "parentPhone": "9876543009",
        "parentRelation": "mother",
        "year": 1,
        "semester": 1,
        "hostelName": "Boys  Hostel A",
        "warden": "Mr. Ramesh Chand",
        "fa": "Dr. Bharat Soni",
        "messName": "Mess B",
        "bankName": "SBI",
        "bankAccountNumber": "10020001234567",
        "bankIfsc": "SBIN0001234",
        "startDate": "2026-02-23",
        "endDate": "2026-02-27",
        "totalDays": 5,
        "reason": "txryjhk",
        "status": "Pending Warden Approval",
        "refundStatus": "Awaiting Approval",
        "name": "Ryan Manchanda",
        "branch": "Computer Science",
        "roomNumber": "A-101",
        "email": "cs25b1034@iiitr.ac.in"
    },
    {
        "fullName": "Ryan Manchanda",
        "rollNumber": "CS25B1034",
        "fatherName": "Rishi Manchanda",
        "motherName": "Mrs. Manchanda",
        "phone": "9234567890",
        "fatherPhone": "9501453725",
        "motherPhone": "9876543009",
        "parentPhone": "9501453725",
        "parentRelation": "father",
        "year": 1,
        "semester": 1,
        "hostelName": "Boys  Hostel A",
        "warden": "Mr. Ramesh Chand",
        "fa": "Dr. Bharat Soni",
        "messName": "Mess B",
        "bankName": "SBI",
        "bankAccountNumber": "10020001234567",
        "bankIfsc": "SBIN0001234",
        "startDate": "2026-02-24",
        "endDate": "2026-02-27",
        "totalDays": 4,
        "reason": "vsdfsd",
        "status": "Pending Warden Approval",
        "familyApproval": "Skipped",
        "wardenApproval": "Pending",
        "faApproval": "Pending",
        "refundStatus": "Awaiting Approval",
        "name": "Ryan Manchanda",
        "branch": "Computer Science",
        "roomNumber": "A-101",
        "email": "cs25b1034@iiitr.ac.in"
    },
    {
        "fullName": "Ryan Manchanda",
        "rollNumber": "CS25B1034",
        "fatherName": "Rishi Manchanda",
        "motherName": "Mrs. Manchanda",
        "phone": "9234567890",
        "fatherPhone": "9501453725",
        "motherPhone": "9876543009",
        "parentPhone": "9501453725",
        "parentRelation": "father",
        "year": 1,
        "semester": 1,
        "hostelName": "Boys  Hostel A",
        "warden": "Mr. Ramesh Chand",
        "fa": "Dr. Bharat Soni",
        "messName": "Mess B",
        "bankName": "SBI",
        "bankAccountNumber": "10020001234567",
        "bankIfsc": "SBIN0001234",
        "startDate": "2026-03-18",
        "endDate": "2026-03-28",
        "totalDays": 11,
        "reason": "fj ndc",
        "status": "Pending Warden Approval",
        "familyApproval": "Skipped",
        "wardenApproval": "Pending",
        "faApproval": "Pending",
        "refundStatus": "Awaiting Approval"
    }
]
